fordpass1/__init__.py
fordpass1/fordpass1.py
fordpass1-0.0.6.data/scripts/demo.py
fordpass1-0.0.6.dist-info/LICENSE.md
fordpass1-0.0.6.dist-info/METADATA
fordpass1-0.0.6.dist-info/WHEEL
fordpass1-0.0.6.dist-info/top_level.txt
fordpass1-0.0.6.dist-info/RECORD
