Metadata-Version: 2.1
Name: fordpass1
Version: 0.0.6
Summary: Python wrapper for the FordPass API for Ford vehicle information and control: start, stop, lock, unlock.
Home-page: https://github.com/cddu33/fordpass-python
Author: Dave Clarke
Author-email: info@daveclarke.me
License: MIT
Platform: UNKNOWN
Classifier: Programming Language :: Python :: 3.9
Classifier: Programming Language :: Python :: 3.8
Classifier: Programming Language :: Python :: 3.7
Classifier: Programming Language :: Python :: 3
Classifier: License :: OSI Approved :: MIT License
Classifier: Operating System :: OS Independent
License-File: LICENSE.md
Requires-Dist: requests
